asto/__init__.py
asto/_modidx.py
asto/arng.py
asto/arrs.py
asto/atyp.py
asto/bend.py
asto/cast.py
asto/chns.py
asto/cons.py
asto/dict.py
asto/nums.py
asto/path.py
asto/sets.py
asto/slcs.py
asto/tens.py
asto/time.py
asto-0.0.34.dist-info/LICENSE
asto-0.0.34.dist-info/METADATA
asto-0.0.34.dist-info/WHEEL
asto-0.0.34.dist-info/entry_points.txt
asto-0.0.34.dist-info/top_level.txt
asto-0.0.34.dist-info/RECORD
