Metadata-Version: 2.1
Name: asto
Version: 0.0.34
Summary: asto
Home-page: https://github.com/dsm-72/asto
Author: dsm-72
Author-email: sumner.magruder@yale.edu
License: Apache Software License 2.0
Keywords: as to convert from one type another
Classifier: Development Status :: 4 - Beta
Classifier: Intended Audience :: Developers
Classifier: Natural Language :: English
Classifier: Programming Language :: Python :: 3.11
Classifier: License :: OSI Approved :: Apache Software License
Requires-Python: >=3.11
License-File: LICENSE
Requires-Dist: nchr
Requires-Dist: nlit
Requires-Dist: quac
Requires-Dist: chck
Requires-Dist: dref
Requires-Dist: sigr
Provides-Extra: dev
Requires-Dist: numpy >=1.22 ; extra == 'dev'
Requires-Dist: torch ; extra == 'dev'
Requires-Dist: anndata ; extra == 'dev'
Requires-Dist: scipy ; extra == 'dev'
Requires-Dist: pytorch-lightning ; extra == 'dev'
